echartslib/__init__.py
echartslib/utils.cp39-win_amd64.pyd
echartslib/calculation/__init__.py
echartslib/calculation/utils.py
echartslib/plot/__init__.py
echartslib/plot/func.cp39-win_amd64.pyd
echartslib/plot/other_widget.cp39-win_amd64.pyd
echartslib/plot/result.cp39-win_amd64.pyd
echartslib/plot/sampler.cp39-win_amd64.pyd
echartslib/plot/utils.cp39-win_amd64.pyd
echartslib/plot/axis/__init__.py
echartslib/plot/axis/base.cp39-win_amd64.pyd
echartslib/plot/axis/component.cp39-win_amd64.pyd
echartslib/plot/axis/style.cp39-win_amd64.pyd
echartslib/plot/component/__init__.py
echartslib/plot/component/animation.cp39-win_amd64.pyd
echartslib/plot/component/brush.cp39-win_amd64.pyd
echartslib/plot/component/datazoom.cp39-win_amd64.pyd
echartslib/plot/component/figsize.cp39-win_amd64.pyd
echartslib/plot/component/grid.cp39-win_amd64.pyd
echartslib/plot/component/legend.cp39-win_amd64.pyd
echartslib/plot/component/style.cp39-win_amd64.pyd
echartslib/plot/component/title.cp39-win_amd64.pyd
echartslib/plot/component/toolbox.cp39-win_amd64.pyd
echartslib/plot/component/tooltip.cp39-win_amd64.pyd
echartslib/plot/component/visualmap.cp39-win_amd64.pyd
echartslib/plot/events/__init__.py
echartslib/plot/events/event.cp39-win_amd64.pyd
echartslib/plot/plots/__init__.py
echartslib/plot/plots/barplot.cp39-win_amd64.pyd
echartslib/plot/plots/barstemplot.cp39-win_amd64.pyd
echartslib/plot/plots/base.cp39-win_amd64.pyd
echartslib/plot/plots/boxplot.cp39-win_amd64.pyd
echartslib/plot/plots/densityplot.cp39-win_amd64.pyd
echartslib/plot/plots/graphplot.cp39-win_amd64.pyd
echartslib/plot/plots/heatmapplot.cp39-win_amd64.pyd
echartslib/plot/plots/histogramplot.cp39-win_amd64.pyd
echartslib/plot/plots/lineplot.cp39-win_amd64.pyd
echartslib/plot/plots/radarplot.cp39-win_amd64.pyd
echartslib/plot/plots/scatter3Dplot.cp39-win_amd64.pyd
echartslib/plot/plots/scatterplot.cp39-win_amd64.pyd
echartslib/plot/plots/text.cp39-win_amd64.pyd
echartslib/plot/plots/treeplot.cp39-win_amd64.pyd
EchartsLib-0.2.0.dist-info/METADATA
EchartsLib-0.2.0.dist-info/WHEEL
EchartsLib-0.2.0.dist-info/top_level.txt
EchartsLib-0.2.0.dist-info/RECORD
