Metadata-Version: 2.1
Name: EchartsLib
Version: 0.2.0
Summary: An interactive data visualization package in Python.
Author: NablaTech
License: Apache
Classifier: Programming Language :: Python :: 3.7
Classifier: Programming Language :: Python :: 3.8
Classifier: Programming Language :: Python :: 3.9
Classifier: License :: OSI Approved :: Apache Software License
Requires-Dist: ipython (>=7.12.0)
Requires-Dist: uvicorn
Requires-Dist: fastapi
Requires-Dist: numpy (>=1.21.4)
Requires-Dist: scipy (>=1.5.3)
Requires-Dist: matplotlib (>=3.1.2)
Requires-Dist: scikit-learn (>=0.24.2)
Requires-Dist: twinning (>=1.0)
Requires-Dist: packaging (>=20.5)
